odoo/addons/sales_team_security_crm/README.rst
odoo/addons/sales_team_security_crm/__init__.py
odoo/addons/sales_team_security_crm/__manifest__.py
odoo/addons/sales_team_security_crm/i18n/it.po
odoo/addons/sales_team_security_crm/i18n/sales_team_security_crm.pot
odoo/addons/sales_team_security_crm/readme/CONTRIBUTORS.md
odoo/addons/sales_team_security_crm/readme/DESCRIPTION.md
odoo/addons/sales_team_security_crm/security/security.xml
odoo/addons/sales_team_security_crm/static/description/icon.png
odoo/addons/sales_team_security_crm/static/description/index.html
odoo/addons/sales_team_security_crm/tests/__init__.py
odoo/addons/sales_team_security_crm/tests/test_sales_team_security_crm.py
odoo_addon_sales_team_security_crm-17.0.1.0.0.3.dist-info/METADATA
odoo_addon_sales_team_security_crm-17.0.1.0.0.3.dist-info/WHEEL
odoo_addon_sales_team_security_crm-17.0.1.0.0.3.dist-info/top_level.txt
odoo_addon_sales_team_security_crm-17.0.1.0.0.3.dist-info/RECORD
